src/__init__.py
src/exceptions.py
src/plugin.py
src/runtime_settings.py
src/utils.py
src/work_items_utils.py
src/hooks_utils/collection_modifyitems.py
src/hooks_utils/configure.py
src/hooks_utils/logs.py
src/hooks_utils/terminal_summary.py
pytest_typhoon_polarion-1.0.3.dist-info/LICENSE
pytest_typhoon_polarion-1.0.3.dist-info/METADATA
pytest_typhoon_polarion-1.0.3.dist-info/WHEEL
pytest_typhoon_polarion-1.0.3.dist-info/entry_points.txt
pytest_typhoon_polarion-1.0.3.dist-info/top_level.txt
pytest_typhoon_polarion-1.0.3.dist-info/RECORD
