Metadata-Version: 2.1
Name: pytest-typhoon-polarion
Version: 1.0.3
Summary: Typhoontest plugin for Siemens Polarion
Author-email: Tiarles Moralles Guterres <tiarles.moralles@typhoon-hil.com>
Maintainer-email: Tiarles Moralles Guterres <tiarles.moralles@typhoon-hil.com>
License: MIT
Project-URL: homepage, https://github.com/typhoon-hil/pytest-typhoon-polarion
Classifier: Development Status :: 4 - Beta
Classifier: Framework :: Pytest
Classifier: Intended Audience :: Developers
Classifier: Programming Language :: Python
Classifier: Programming Language :: Python :: 3
Classifier: Programming Language :: Python :: 3.8
Classifier: Programming Language :: Python :: 3.9
Classifier: Programming Language :: Python :: 3.10
Classifier: Programming Language :: Python :: 3.11
Classifier: License :: OSI Approved :: MIT License
Requires-Python: >=3.8
License-File: LICENSE
Requires-Dist: typhoontest >=1.27.0
Requires-Dist: polarion ==1.3.0
Requires-Dist: configparser
